{
  "PackageData": [
    {
      "Row": [
        {
          "SchemaColumnUId": "ae0e45ca-c495-4fe7-a39d-3ab7278e1617",
          "ColumnName": "Id",
          "Value": "f27813dd-349e-46de-81cc-6d31718deb29"
        },
        {
          "SchemaColumnUId": "009571ab-9c5d-4a20-bf83-dd499ed5a833",
          "ColumnName": "Description",
          "Value": ""
        },
        {
          "SchemaColumnUId": "547bff8d-f717-4316-846c-3ff1f0e36e6e",
          "ColumnName": "Name",
          "Value": ""
        }
      ]
    },
    {
      "Row": [
        {
          "SchemaColumnUId": "ae0e45ca-c495-4fe7-a39d-3ab7278e1617",
          "ColumnName": "Id",
          "Value": "123162f9-bf38-445e-907d-9242fc85dd41"
        },
        {
          "SchemaColumnUId": "009571ab-9c5d-4a20-bf83-dd499ed5a833",
          "ColumnName": "Description",
          "Value": ""
        },
        {
          "SchemaColumnUId": "547bff8d-f717-4316-846c-3ff1f0e36e6e",
          "ColumnName": "Name",
          "Value": ""
        }
      ]
    },
    {
      "Row": [
        {
          "SchemaColumnUId": "ae0e45ca-c495-4fe7-a39d-3ab7278e1617",
          "ColumnName": "Id",
          "Value": "4a98903a-b325-4c74-8719-a150f6b9e856"
        },
        {
          "SchemaColumnUId": "009571ab-9c5d-4a20-bf83-dd499ed5a833",
          "ColumnName": "Description",
          "Value": ""
        },
        {
          "SchemaColumnUId": "547bff8d-f717-4316-846c-3ff1f0e36e6e",
          "ColumnName": "Name",
          "Value": ""
        }
      ]
    }
  ]
}